{
    "_id": "https://www.tianyancha.com/company/2349731807",
    "标题": "滁州建城投资基金合伙企业（有限合伙）",
    "标题链接": "https://www.tianyancha.com/company/2349731807",
    "一般纳税人": [
        {
            "序号": "1",
            "纳税人名称": "建城投资\n\t滁州建城投资基金合伙企业（有限合伙）\n[滁州建城投资基金合伙企业（有限合伙）](https://www.tianyancha.com/company/2349731807)",
            "纳税人识别号": "91341100MA2MRBB67T",
            "纳税人资格类型": "一般纳税人",
            "主管税务机关": "国家税务总局滁州经济技术开发区税务局",
            "有效期止": "-"
        }
    ],
    "一般纳税人_数量": 1,
    "企业年报_数量": 5,
    "历史动产抵押_数量": 0,
    "历史司法协助_数量": 0,
    "历史合伙人信息_数量": 1,
    "历史商标信息_数量": 0,
    "历史土地抵押_数量": 0,
    "历史失信被执行人_数量": 0,
    "历史对外投资_数量": 0,
    "历史工商信息_数量": 0,
    "历史开庭公告_数量": 0,
    "历史执行事务合伙人_数量": 0,
    "历史欠税公告_数量": 0,
    "历史法律诉讼_数量": 0,
    "历史法院公告_数量": 0,
    "历史知识产权出质_数量": 0,
    "历史终本案件_数量": 0,
    "历史经营异常_数量": 0,
    "历史网站备案_数量": 0,
    "历史股东镜像_数量": 2,
    "历史股权出质_数量": 0,
    "历史行政处罚_数量": 0,
    "历史行政许可_数量": 1,
    "历史被执行人_数量": 0,
    "历史限制消费令_数量": 0,
    "变更记录": [
        {
            "序号": "1",
            "变更日期": "2017-04-12",
            "变更项目": "投资人变更（包括出资额、出资方式、出资日期、投资人名称等）",
            "变更前": "建信资本管理有限责任公司; [退出]\n\n皖江产业转移投资基金（安徽）管理有限公司;\n\n滁州市城市建设投资有限公司;\n[建信资本管理有限责任公司](https://www.tianyancha.com/company/142635126)\n[皖江产业转移投资基金（安徽）管理有限公司](https://www.tianyancha.com/company/3462455542)\n[滁州市城市建设投资有限公司](https://www.tianyancha.com/company/3469135498)",
            "变更后": "建信（北京）投资基金管理有限责任公司; [新增]\n\n皖江产业转移投资基金（安徽）管理有限公司;\n\n滁州市城市建设投资有限公司;\n[建信（北京）投资基金管理有限责任公司](https://www.tianyancha.com/company/18218240)\n[皖江产业转移投资基金（安徽）管理有限公司](https://www.tianyancha.com/company/3462455542)\n[滁州市城市建设投资有限公司](https://www.tianyancha.com/company/3469135498)"
        }
    ],
    "变更记录_数量": 1,
    "司法风险_数量": 0,
    "合伙人信息": [
        {
            "序号": "1",
            "股东（发起人）": "建信（北\n\t建信（北京）投资基金管理有限责任公司\n大股东\n\t\n[建信（北京）投资基金管理有限责任公司](https://www.tianyancha.com/company/18218240)",
            "持股比例": "79.97%",
            "最终受益股份": "79.97%\n",
            "": "444000.0万元人民币",
            "认缴出资日期": "-"
        },
        {
            "序号": "2",
            "股东（发起人）": "滁州市城\n\t滁州市城市投资控股集团有限公司\n曾用名\n滁州市城市建设投资有限公司\n(2008-05 至 2020-08)\n\t\n[滁州市城市投资控股集团有限公司](https://www.tianyancha.com/company/3469135498)",
            "持股比例": "19.99%",
            "最终受益股份": "19.99%\n",
            "": "111000.0万元人民币",
            "认缴出资日期": "-"
        },
        {
            "序号": "3",
            "股东（发起人）": "建银皖江\n\t建银皖江产业基金管理（安徽）有限公司\n曾用名\n皖江产业转移投资基金（安徽）管理有限公司\n(2009-10 至 2020-08)\n\t\n[建银皖江产业基金管理（安徽）有限公司](https://www.tianyancha.com/company/3462455542)",
            "持股比例": "0.04%",
            "最终受益股份": "0.04%\n",
            "": "200.0万元人民币",
            "认缴出资日期": "-"
        }
    ],
    "合伙人信息_数量": 3,
    "工商信息": [
        {
            "执行事务合伙人": "皖江产业\n\t皖江产业转移投资基金（安徽）管理有限公司\n[皖江产业转移投资基金（安徽）管理有限公司](https://www.tianyancha.com/company/1043862341)",
            "经营状态": "注销",
            "天眼评分": "评分99",
            "成立日期": "2015-12-14",
            "出资额": "555200万人民币",
            "实缴资本": "-",
            "工商注册号": "341191000000805",
            "统一社会信用代码": "",
            "纳税人识别号": "",
            "组织机构代码": "",
            "营业期限": "2015-12-14  至 2020-12-13",
            "纳税人资质": "-",
            "核准日期": "2020-07-28",
            "企业类型": "有限合伙企业",
            "行业": "商务服务业",
            "人员规模": "-",
            "参保人数": "0",
            "登记机关": "滁州经济技术开发区市场监督管理局",
            "曾用名": "-",
            "英文名称": "",
            "主要经营场所": "附近公司\n[附近公司](https://www.tianyancha.com/map/2349731807)",
            "经营范围": "投资及资产管理、投资咨询。（依法须经批准的项目，经相关部门批准后方可开展经营活动）"
        }
    ],
    "工商信息_数量": 3,
    "投资机构": [
        {
            "序号": "1",
            "投资机构": "暂无\n\t皖江产业\n[皖江产业](https://www.tianyancha.com/organize/bb25813331)",
            "成立日期": "2009年",
            "所属地": "安徽",
            "简介": "皖江产业转移投资基金（安徽）管理有限公司是皖江城市带承接产业转移投资基金的投资管理平台，由建银国际财富有限公司控股，与安徽徽商创业投资基金行（有限合伙）共同设立。皖江产业转移投资基金(安徽)管理有限公司是一支PE投资基金专业管理团队，服务于皖江城市带承接产业转移示范区内的各行企业。  "
        }
    ],
    "投资机构_数量": 1,
    "清算信息": [
        {
            "清算组负责人": "冯峰",
            "清算组成员": "郑佳佳、朱江"
        }
    ],
    "清算信息_数量": 1,
    "知识产权_数量": 0,
    "自主信息_数量": 0,
    "行政许可": [
        {
            "序号": "1",
            "决定日期/有效期自": "2017-04-12",
            "截止日期/有效期至": "2099年12月31日",
            "许可文件编号/文书号": "6387",
            "许可文件名称": "滁州建城投资基金合伙企业(有限合伙)登记",
            "决定/许可机关": "滁州市工商行政管理局",
            "许可内容": "投资及资产管理、投资咨询。(依法须经批准的项目,经相关部门批准后方可开展经营活动)  ",
            "数据来源": "国家市场监督管理总局",
            "操作": "            {\"licenceContent\":\"投资及资产管理、投资咨询。(依法须经批准的项目,经相关部门批准后方可开展经营活动)\",\"sourceId\":1,\"detailBusinessId\":\"7m9c4momc58927e19bff67172lf44ba9\",\"gid\":2349731807,\"endDate\":\"2099年12月31日\",\"licenceName\":\"滁州建城投资基金合伙企业(有限合伙)登记\",\"licenceNumber\":\"6387\",\"showTypeName\":\"国家市场监督管理总局\",\"detailShowType\":1,\"similarId\":0,\"fromDate\":\"2017-04-12\",\"licenceDepartment\":\"滁州市工商行政管理局\",\"id\":27051763,\"originalId\":387018480,\"similarCount\":0}          "
        }
    ],
    "行政许可_数量": 1,
    "解析于": "2021-11-04T07:31:31.271Z",
    "解析账号": {
        "_id": "15697089347",
        "账号": 15697089347,
        "用户名": "赵子龙"
    },
    "最终受益人_数量": 1,
    "疑似实际控制人_数量": 0
}