{
    "_id": "https://www.tianyancha.com/company/3367308",
    "标题": "北京市民政局",
    "标题链接": "https://www.tianyancha.com/company/3367308",
    "主要负责人": [
        {
            "序号": "1",
            "姓名": "李万钧",
            "人员类型": "负责人"
        }
    ],
    "主要负责人_数量": 1,
    "作品著作权": [
        {
            "序号": "1",
            "作品名称": "“首都社工”徽章",
            "登记号": "国作登字-2015-F-00193060",
            "作品类别": "美术",
            "创作完成日期": "2014-04-29",
            "登记日期": "2015-06-12",
            "首次发表日期": "-"
        },
        {
            "序号": "2",
            "作品名称": "“首都社工”宣传标识",
            "登记号": "国作登字-2015-F-00193061",
            "作品类别": "美术",
            "创作完成日期": "2014-10-23",
            "登记日期": "2015-06-12",
            "首次发表日期": "-"
        }
    ],
    "作品著作权_数量": 2,
    "供应商": [
        {
            "序号": "1",
            "供应商": "中工国际\n\t\n中工国际招标有限公司\n[中工国际招标有限公司](https://www.tianyancha.com/company/2313873717)",
            "采购占比": "-",
            "采购金额": "8.76万元",
            "报告期": "2021-10-25",
            "数据来源": "招投标公告\n[招投标公告](https://www.tianyancha.com/bid/3824cfa0d5f54392a9388659f3a60683)",
            "关联关系": "-"
        },
        {
            "序号": "2",
            "供应商": "宏信天诚\n\t\n北京宏信天诚国际招标有限公司\n[北京宏信天诚国际招标有限公司](https://www.tianyancha.com/company/12895743)",
            "采购占比": "-",
            "采购金额": "2.40万元",
            "报告期": "2021-10-25",
            "数据来源": "招投标公告\n[招投标公告](https://www.tianyancha.com/bid/d2b21b957b8b4ccf83c6ab92e4d5893a)",
            "关联关系": "-"
        },
        {
            "序号": "3",
            "供应商": "中永智\n\t\n北京中永智会计师事务所有限公司\n[北京中永智会计师事务所有限公司](https://www.tianyancha.com/company/32017502)",
            "采购占比": "-",
            "采购金额": "12.80万元",
            "报告期": "2021-10-21",
            "数据来源": "招投标公告\n[招投标公告](https://www.tianyancha.com/bid/a874f7de7b6d430eab87508a8ff70f09)",
            "关联关系": "-"
        },
        {
            "序号": "4",
            "供应商": "刁文鲳\n\t\n刁文鲳健康管理（北京）有限公司\n[刁文鲳健康管理（北京）有限公司](https://www.tianyancha.com/company/5052006983)",
            "采购占比": "-",
            "采购金额": "11.91万元",
            "报告期": "2021-10-15",
            "数据来源": "招投标公告\n[招投标公告](https://www.tianyancha.com/bid/d09e1d2b761f4c1cb2a32d941a9e7073)",
            "关联关系": "-"
        },
        {
            "序号": "5",
            "供应商": "中诚信安\n\t\n中诚信安瑞（北京）会计师事务所有限公司\n[中诚信安瑞（北京）会计师事务所有限公司](https://www.tianyancha.com/company/16510066)",
            "采购占比": "-",
            "采购金额": "44.50万元",
            "报告期": "2021-10-15",
            "数据来源": "招投标公告\n[招投标公告](https://www.tianyancha.com/bid/e942f269c2f44315bbb4db33e22f9216)",
            "关联关系": "-"
        },
        {
            "序号": "6",
            "供应商": "社会治理\n\t\n中国社会治理研究会\n[中国社会治理研究会](https://www.tianyancha.com/company/3078017433)",
            "采购占比": "-",
            "采购金额": "17.59万元",
            "报告期": "2021-10-11",
            "数据来源": "招投标公告\n[招投标公告](https://www.tianyancha.com/bid/041ae5fa661c441e84ba6ff99d0f3f49)",
            "关联关系": "-"
        },
        {
            "序号": "7",
            "供应商": "方舟\n\t\n北京市朝阳区方舟社会工作发展中心\n[北京市朝阳区方舟社会工作发展中心](https://www.tianyancha.com/company/3079064916)",
            "采购占比": "-",
            "采购金额": "14.59万元",
            "报告期": "2021-10-09",
            "数据来源": "招投标公告\n[招投标公告](https://www.tianyancha.com/bid/1c93cec7041f48b687000dd8cc0fa03f)",
            "关联关系": "-"
        },
        {
            "序号": "8",
            "供应商": "瀚海博越\n\t\n北京瀚海博越科技有限公司\n[北京瀚海博越科技有限公司](https://www.tianyancha.com/company/4328142201)",
            "采购占比": "-",
            "采购金额": "156.50万元",
            "报告期": "2021-10-09",
            "数据来源": "招投标公告\n[招投标公告](https://www.tianyancha.com/bid/903180caeacf49b8b8c5b60627e0a46e)",
            "关联关系": "-"
        },
        {
            "序号": "9",
            "供应商": "七悦社会\n\t\n北京七悦社会公益服务中心\n[北京七悦社会公益服务中心](https://www.tianyancha.com/company/3079060658)",
            "采购占比": "-",
            "采购金额": "37.28万元",
            "报告期": "2021-10-09",
            "数据来源": "招投标公告\n[招投标公告](https://www.tianyancha.com/bid/67b7404becb44b66a438392ce1999ed7)",
            "关联关系": "-"
        },
        {
            "序号": "10",
            "供应商": "同乐和\n\t\n北京同乐和社会工作事务所\n[北京同乐和社会工作事务所](https://www.tianyancha.com/company/3079066898)",
            "采购占比": "-",
            "采购金额": "28.31万元",
            "报告期": "2021-10-08",
            "数据来源": "招投标公告\n[招投标公告](https://www.tianyancha.com/bid/3e1f692cfb304605ab771be66e93cd7e)",
            "关联关系": "-"
        }
    ],
    "供应商_数量": 234,
    "公司发展_数量": 0,
    "历史动产抵押_数量": 0,
    "历史司法协助_数量": 0,
    "历史商标信息_数量": 0,
    "历史土地抵押_数量": 0,
    "历史失信被执行人_数量": 0,
    "历史对外投资_数量": 1,
    "历史开庭公告_数量": 0,
    "历史欠税公告_数量": 0,
    "历史法律诉讼_数量": 0,
    "历史法院公告_数量": 0,
    "历史知识产权出质_数量": 0,
    "历史终本案件_数量": 0,
    "历史经营异常_数量": 0,
    "历史网站备案_数量": 2,
    "历史股权出质_数量": 0,
    "历史行政处罚_数量": 0,
    "历史行政许可_数量": 0,
    "历史被执行人_数量": 0,
    "历史限制消费令_数量": 0,
    "司法风险_数量": 0,
    "对外投资": [
        {
            "序号": "1",
            "被投资企业名称": "康复辅具\n\t\n北京市康复辅具技术中心\n[北京市康复辅具技术中心](https://www.tianyancha.com/company/3114771762)",
            "法定代表人": "-",
            "成立日期": "1981-12-18",
            "投资数额": "600万人民币",
            "投资比例": "100%",
            "经营状态": "注销",
            "关联产品": "-",
            "关联机构": "-"
        },
        {
            "序号": "2",
            "被投资企业名称": "民政实业\n\t\n北京市民政实业开发公司\n[北京市民政实业开发公司](https://www.tianyancha.com/company/2320404653)",
            "法定代表人": "张\n\t\n张晓敏\n任职1家企业\n[张晓敏](https://www.tianyancha.com/human/1927204063-c2320404653)\n[任职1家企业](https://www.tianyancha.com/human/1927204063-c2320404653)",
            "法定代表人_名字": "张晓敏",
            "法定代表人_链接": "https://www.tianyancha.com/human/1927204063-c2320404653",
            "成立日期": "-",
            "投资数额": "254.3万元",
            "投资比例": "100%",
            "经营状态": "注销",
            "关联产品": "-",
            "关联机构": "-"
        },
        {
            "序号": "3",
            "被投资企业名称": "岳各庄福\n\t\n北京市岳各庄福利园艺场\n[北京市岳各庄福利园艺场](https://www.tianyancha.com/company/2319789445)",
            "法定代表人": "赵\n\t\n赵仲臭\n任职2家企业\n[赵仲臭](https://www.tianyancha.com/human/2319121891-c2319789445)\n[任职2家企业](https://www.tianyancha.com/human/2319121891-c2319789445)",
            "法定代表人_名字": "赵仲臭",
            "法定代表人_链接": "https://www.tianyancha.com/human/2319121891-c2319789445",
            "成立日期": "-",
            "投资数额": "22.4万元",
            "投资比例": "100%",
            "经营状态": "吊销",
            "关联产品": "-",
            "关联机构": "-"
        },
        {
            "序号": "4",
            "被投资企业名称": "威龙\n\t\n北京市海淀区威龙汽车修理服务部\n[北京市海淀区威龙汽车修理服务部](https://www.tianyancha.com/company/2319311792)",
            "法定代表人": "徐\n\t\n徐锁华\n任职1家企业\n[徐锁华](https://www.tianyancha.com/human/1944263874-c2319311792)\n[任职1家企业](https://www.tianyancha.com/human/1944263874-c2319311792)",
            "法定代表人_名字": "徐锁华",
            "法定代表人_链接": "https://www.tianyancha.com/human/1944263874-c2319311792",
            "成立日期": "-",
            "投资数额": "0",
            "投资比例": "100%",
            "经营状态": "注销",
            "关联产品": "-",
            "关联机构": "-"
        },
        {
            "序号": "5",
            "被投资企业名称": "利民橡\n\t\n北京市利民橡塑制品厂\n[北京市利民橡塑制品厂](https://www.tianyancha.com/company/2319241561)",
            "法定代表人": "王\n\t\n王东升\n任职1家企业\n[王东升](https://www.tianyancha.com/human/2064477261-c2319241561)\n[任职1家企业](https://www.tianyancha.com/human/2064477261-c2319241561)",
            "法定代表人_名字": "王东升",
            "法定代表人_链接": "https://www.tianyancha.com/human/2064477261-c2319241561",
            "成立日期": "-",
            "投资数额": "0",
            "投资比例": "100%",
            "经营状态": "注销",
            "关联产品": "-",
            "关联机构": "-"
        },
        {
            "序号": "6",
            "被投资企业名称": "海淀京福\n\t\n北京市海淀京福交通设备经营部\n[北京市海淀京福交通设备经营部](https://www.tianyancha.com/company/2319218159)",
            "法定代表人": "张\n\t\n张庆长\n任职1家企业\n[张庆长](https://www.tianyancha.com/human/1925256182-c2319218159)\n[任职1家企业](https://www.tianyancha.com/human/1925256182-c2319218159)",
            "法定代表人_名字": "张庆长",
            "法定代表人_链接": "https://www.tianyancha.com/human/1925256182-c2319218159",
            "成立日期": "-",
            "投资数额": "0",
            "投资比例": "100%",
            "经营状态": "注销",
            "关联产品": "-",
            "关联机构": "-"
        },
        {
            "序号": "7",
            "被投资企业名称": "飞鸿\n\t\n北京飞鸿广告公司\n[北京飞鸿广告公司](https://www.tianyancha.com/company/2319189439)",
            "法定代表人": "张\n\t\n张小明\n任职1家企业\n[张小明](https://www.tianyancha.com/human/1924675337-c2319189439)\n[任职1家企业](https://www.tianyancha.com/human/1924675337-c2319189439)",
            "法定代表人_名字": "张小明",
            "法定代表人_链接": "https://www.tianyancha.com/human/1924675337-c2319189439",
            "成立日期": "-",
            "投资数额": "100万元",
            "投资比例": "100%",
            "经营状态": "吊销",
            "关联产品": "-",
            "关联机构": "-"
        },
        {
            "序号": "8",
            "被投资企业名称": "雅兴商贸\n\t\n北京市雅兴商贸公司\n[北京市雅兴商贸公司](https://www.tianyancha.com/company/2319064958)",
            "法定代表人": "高\n\t\n高永利\n任职1家企业\n[高永利](https://www.tianyancha.com/human/2286009764-c2319064958)\n[任职1家企业](https://www.tianyancha.com/human/2286009764-c2319064958)",
            "法定代表人_名字": "高永利",
            "法定代表人_链接": "https://www.tianyancha.com/human/2286009764-c2319064958",
            "成立日期": "1900-01-01",
            "投资数额": "0",
            "投资比例": "100%",
            "经营状态": "吊销，已注销",
            "关联产品": "-",
            "关联机构": "-"
        },
        {
            "序号": "9",
            "被投资企业名称": "方兴圆\n\t\n北京市方兴圆汽车修理站\n[北京市方兴圆汽车修理站](https://www.tianyancha.com/company/2319040554)",
            "法定代表人": "韩\n\t\n韩金才\n任职1家企业\n[韩金才](https://www.tianyancha.com/human/2271790845-c2319040554)\n[任职1家企业](https://www.tianyancha.com/human/2271790845-c2319040554)",
            "法定代表人_名字": "韩金才",
            "法定代表人_链接": "https://www.tianyancha.com/human/2271790845-c2319040554",
            "成立日期": "-",
            "投资数额": "45万元",
            "投资比例": "100%",
            "经营状态": "吊销",
            "关联产品": "-",
            "关联机构": "-"
        },
        {
            "序号": "10",
            "被投资企业名称": "创世卡通\n\t\n北京市创世卡通设计公司\n[北京市创世卡通设计公司](https://www.tianyancha.com/company/2318923019)",
            "法定代表人": "范\n\t\n范家泰\n任职1家企业\n[范家泰](https://www.tianyancha.com/human/2318923020-c2318923019)\n[任职1家企业](https://www.tianyancha.com/human/2318923020-c2318923019)",
            "法定代表人_名字": "范家泰",
            "法定代表人_链接": "https://www.tianyancha.com/human/2318923020-c2318923019",
            "成立日期": "-",
            "投资数额": "50万元",
            "投资比例": "100%",
            "经营状态": "注销",
            "关联产品": "-",
            "关联机构": "-"
        },
        {
            "序号": "11",
            "被投资企业名称": "正通和顺\n\t\n北京正通和顺技术工程公司\n[北京正通和顺技术工程公司](https://www.tianyancha.com/company/2318906207)",
            "法定代表人": "乔\n\t\n乔宗啟\n任职1家企业\n[乔宗啟](https://www.tianyancha.com/human/2318906208-c2318906207)\n[任职1家企业](https://www.tianyancha.com/human/2318906208-c2318906207)",
            "法定代表人_名字": "乔宗啟",
            "法定代表人_链接": "https://www.tianyancha.com/human/2318906208-c2318906207",
            "成立日期": "-",
            "投资数额": "35万元",
            "投资比例": "100%",
            "经营状态": "注销",
            "关联产品": "-",
            "关联机构": "-"
        },
        {
            "序号": "12",
            "被投资企业名称": "豪门酒家\n\t\n北京市豪门酒家\n[北京市豪门酒家](https://www.tianyancha.com/company/2318833054)",
            "法定代表人": "刘\n\t\n刘宝林\n任职1家企业\n[刘宝林](https://www.tianyancha.com/human/1810162069-c2318833054)\n[任职1家企业](https://www.tianyancha.com/human/1810162069-c2318833054)",
            "法定代表人_名字": "刘宝林",
            "法定代表人_链接": "https://www.tianyancha.com/human/1810162069-c2318833054",
            "成立日期": "-",
            "投资数额": "60万元",
            "投资比例": "100%",
            "经营状态": "吊销",
            "关联产品": "-",
            "关联机构": "-"
        },
        {
            "序号": "13",
            "被投资企业名称": "殡葬建筑\n\t\n北京市殡葬建筑公司\n[北京市殡葬建筑公司](https://www.tianyancha.com/company/2318577440)",
            "法定代表人": "朱\n\t\n朱德治\n任职1家企业\n[朱德治](https://www.tianyancha.com/human/1973678177-c2318577440)\n[任职1家企业](https://www.tianyancha.com/human/1973678177-c2318577440)",
            "法定代表人_名字": "朱德治",
            "法定代表人_链接": "https://www.tianyancha.com/human/1973678177-c2318577440",
            "成立日期": "-",
            "投资数额": "80万元",
            "投资比例": "100%",
            "经营状态": "注销",
            "关联产品": "-",
            "关联机构": "-"
        },
        {
            "序号": "14",
            "被投资企业名称": "祥和居\n\t\n北京市祥和居饭庄\n[北京市祥和居饭庄](https://www.tianyancha.com/company/2317826843)",
            "法定代表人": "杜\n\t\n杜景国\n任职1家企业\n[杜景国](https://www.tianyancha.com/human/1994871140-c2317826843)\n[任职1家企业](https://www.tianyancha.com/human/1994871140-c2317826843)",
            "法定代表人_名字": "杜景国",
            "法定代表人_链接": "https://www.tianyancha.com/human/1994871140-c2317826843",
            "成立日期": "-",
            "投资数额": "15万元",
            "投资比例": "100%",
            "经营状态": "注销",
            "关联产品": "-",
            "关联机构": "-"
        },
        {
            "序号": "15",
            "被投资企业名称": "汽车灯具\n\t\n北京东城汽车灯具修配厂\n[北京东城汽车灯具修配厂](https://www.tianyancha.com/company/2314429049)",
            "法定代表人": "杨\n\t\n杨玉杰\n任职1家企业\n[杨玉杰](https://www.tianyancha.com/human/2003055451-c2314429049)\n[任职1家企业](https://www.tianyancha.com/human/2003055451-c2314429049)",
            "法定代表人_名字": "杨玉杰",
            "法定代表人_链接": "https://www.tianyancha.com/human/2003055451-c2314429049",
            "成立日期": "-",
            "投资数额": "0",
            "投资比例": "100%",
            "经营状态": "注销",
            "关联产品": "-",
            "关联机构": "-"
        },
        {
            "序号": "16",
            "被投资企业名称": "社会福利\n\t\n北京市社会福利经贸公司\n[北京市社会福利经贸公司](https://www.tianyancha.com/company/2314344009)",
            "法定代表人": "赵\n\t\n赵桂甲\n任职1家企业\n[赵桂甲](https://www.tianyancha.com/human/2314344010-c2314344009)\n[任职1家企业](https://www.tianyancha.com/human/2314344010-c2314344009)",
            "法定代表人_名字": "赵桂甲",
            "法定代表人_链接": "https://www.tianyancha.com/human/2314344010-c2314344009",
            "成立日期": "-",
            "投资数额": "200万元",
            "投资比例": "100%",
            "经营状态": "注销",
            "关联产品": "-",
            "关联机构": "-"
        },
        {
            "序号": "17",
            "被投资企业名称": "市北恒\n\t\n北京市北恒商贸公司\n[北京市北恒商贸公司](https://www.tianyancha.com/company/2313945283)",
            "法定代表人": "姜\n\t\n姜晓刚\n任职1家企业\n[姜晓刚](https://www.tianyancha.com/human/1873821867-c2313945283)\n[任职1家企业](https://www.tianyancha.com/human/1873821867-c2313945283)",
            "法定代表人_名字": "姜晓刚",
            "法定代表人_链接": "https://www.tianyancha.com/human/1873821867-c2313945283",
            "成立日期": "-",
            "投资数额": "80万元",
            "投资比例": "100%",
            "经营状态": "注销",
            "关联产品": "-",
            "关联机构": "-"
        },
        {
            "序号": "18",
            "被投资企业名称": "龙人五金\n\t\n北京市龙人五金电器经营部\n[北京市龙人五金电器经营部](https://www.tianyancha.com/company/2310453039)",
            "法定代表人": "张\n\t\n张秉信\n任职2家企业\n[张秉信](https://www.tianyancha.com/human/1930533078-c2310453039)\n[任职2家企业](https://www.tianyancha.com/human/1930533078-c2310453039)",
            "法定代表人_名字": "张秉信",
            "法定代表人_链接": "https://www.tianyancha.com/human/1930533078-c2310453039",
            "成立日期": "-",
            "投资数额": "0",
            "投资比例": "100%",
            "经营状态": "注销",
            "关联产品": "-",
            "关联机构": "-"
        },
        {
            "序号": "19",
            "被投资企业名称": "福民\n\t\n北京福民旅行社\n[北京福民旅行社](https://www.tianyancha.com/company/1252981061)",
            "法定代表人": "李\n\t\n李新京\n任职7家企业\n[李新京](https://www.tianyancha.com/human/1985209867-c1252981061)\n[任职7家企业](https://www.tianyancha.com/human/1985209867-c1252981061)",
            "法定代表人_名字": "李新京",
            "法定代表人_链接": "https://www.tianyancha.com/human/1985209867-c1252981061",
            "成立日期": "-",
            "投资数额": "30万元",
            "投资比例": "100%",
            "经营状态": "吊销",
            "关联产品": "-",
            "关联机构": "-"
        },
        {
            "序号": "20",
            "被投资企业名称": "龙人\n\t\n北京市龙人地毯厂\n[北京市龙人地毯厂](https://www.tianyancha.com/company/1047534594)",
            "法定代表人": "杨\n\t\n杨怀英\n任职1家企业\n[杨怀英](https://www.tianyancha.com/human/2000647222-c1047534594)\n[任职1家企业](https://www.tianyancha.com/human/2000647222-c1047534594)",
            "法定代表人_名字": "杨怀英",
            "法定代表人_链接": "https://www.tianyancha.com/human/2000647222-c1047534594",
            "成立日期": "-",
            "投资数额": "100万元",
            "投资比例": "100%",
            "经营状态": "吊销",
            "关联产品": "-",
            "关联机构": "-"
        }
    ],
    "对外投资_数量": 23,
    "微信公众号": [
        {
            "序号": "1",
            "微信公众号": "北京社会建设和民政\n\t北京社会建设和民政",
            "微信号": "bjmz_xxzx",
            "二维码": "",
            "简介": "发布权威信息、解读重大政策、讲好民生故事、搭建互动平台  "
        }
    ],
    "微信公众号_数量": 1,
    "标准信息": [
        {
            "序号": "1",
            "标准名称": "养老机构服务质量基本规范",
            "标准编号": "GB/T 35796-2017",
            "标准级别": "国家标准",
            "标准状态": "现行",
            "标准性质": "推荐性",
            "": "2017-12-29",
            "操作": "详情\n[详情](https://www.tianyancha.com/standard/detail/49741c409f257a740560b919dl0a4047)"
        },
        {
            "序号": "2",
            "标准名称": "养老机构基本规范",
            "标准编号": "GB/T 29353-2012",
            "标准级别": "国家标准",
            "标准状态": "现行",
            "标准性质": "推荐性",
            "": "2013-05-01",
            "操作": "详情\n[详情](https://www.tianyancha.com/standard/detail/omv4cc4ff3a55bde8c81ac1c2ldf4037)"
        },
        {
            "序号": "3",
            "标准名称": "救灾被服 第2部分：棉大衣",
            "标准编号": "MZ/T 014.2-2010",
            "标准级别": "行业标准",
            "标准状态": "现行",
            "标准性质": "-",
            "": "2010-03-15",
            "操作": "详情\n[详情](https://www.tianyancha.com/standard/detail/4997m9cvef44c1d824373616fl66m8f8)"
        },
        {
            "序号": "4",
            "标准名称": "救灾被服 第4部分：多功能睡袋",
            "标准编号": "MZ/T 014.4-2010",
            "标准级别": "行业标准",
            "标准状态": "现行",
            "标准性质": "-",
            "": "2010-03-15",
            "操作": "详情\n[详情](https://www.tianyancha.com/standard/detail/497oz4cv0214695499de2f1f4l07z328)"
        },
        {
            "序号": "5",
            "标准名称": "救灾装具 第4部分：气垫床",
            "标准编号": "MZ/T 015.4-2010",
            "标准级别": "行业标准",
            "标准状态": "现行",
            "标准性质": "-",
            "": "2010-03-15",
            "操作": "详情\n[详情](https://www.tianyancha.com/standard/detail/4emocccv1953c0466490e919bl59cbb8)"
        },
        {
            "序号": "6",
            "标准名称": "救灾帐篷 第7部分：帐篷涂层布",
            "标准编号": "MZ/T 011.7-2010",
            "标准级别": "行业标准",
            "标准状态": "现行",
            "标准性质": "-",
            "": "2010-03-15",
            "操作": "详情\n[详情](https://www.tianyancha.com/standard/detail/4vve4mcve5b73a651f3ea414fl824ad8)"
        },
        {
            "序号": "7",
            "标准名称": "救灾装具 第2部分：折叠桌、凳",
            "标准编号": "MZ/T 015.2-2010",
            "标准级别": "行业标准",
            "标准状态": "现行",
            "标准性质": "-",
            "": "2010-03-15",
            "操作": "详情\n[详情](https://www.tianyancha.com/standard/detail/44m1zocv78d5df3c2f4a2f1f9l28zf68)"
        },
        {
            "序号": "8",
            "标准名称": "救灾装具 第1部分：折叠床",
            "标准编号": "MZ/T 015.1-2010",
            "标准级别": "行业标准",
            "标准状态": "现行",
            "标准性质": "-",
            "": "2010-03-15",
            "操作": "详情\n[详情](https://www.tianyancha.com/standard/detail/444ezocvf7a64b5ac8cc7515bl06zce8)"
        },
        {
            "序号": "9",
            "标准名称": "救灾被服 第1部分：棉被",
            "标准编号": "MZ/T 014.1-2010",
            "标准级别": "行业标准",
            "标准状态": "现行",
            "标准性质": "-",
            "": "2010-03-15",
            "操作": "详情\n[详情](https://www.tianyancha.com/standard/detail/4c14o9cv849f27f329d5ee1e7la5o948)"
        },
        {
            "序号": "10",
            "标准名称": "救灾帐篷 第4部分：12㎡棉帐篷",
            "标准编号": "MZ/T 011.4-2010",
            "标准级别": "行业标准",
            "标准状态": "现行",
            "标准性质": "-",
            "": "2010-03-15",
            "操作": "详情\n[详情](https://www.tianyancha.com/standard/detail/9e9vecvb8b9f0169e0de16160lb0v3d7)"
        }
    ],
    "标准信息_数量": 18,
    "涉诉关系_数量": 23,
    "登记信息": [
        {
            "法定代表人/负责人": "李万钧",
            "注册资本": "0万",
            "成立日期": "-",
            "经营状态": "-",
            "批准机构名称/登记管理部门名称": "市政府",
            "经济行业": "未公示",
            "登记号": "未公示",
            "机构类型": "机关",
            "统一社会信用代码": "11110000000021039C",
            "经济类型": "未公示",
            "经营期限": "未公示",
            "注册地址": "北京市朝阳区工人体育场东路20号  ",
            "经营范围": "未公示"
        }
    ],
    "登记信息_数量": 0,
    "经营风险_数量": 0,
    "网站备案_数量": 2,
    "行政许可": [
        {
            "序号": "1",
            "决定日期/有效期自": "2018-09-07",
            "截止日期/有效期至": "2099-12-31",
            "许可文件编号/文书号": "Z1000001091601",
            "许可文件名称": "开户许可",
            "决定/许可机关": "中国人民银行营业管理部",
            "许可内容": "变更  ",
            "数据来源": "中国人民银行",
            "操作": "            {\"licenceContent\":\"变更\",\"sourceId\":3,\"oneSimilarShowType\":2,\"gid\":3367308,\"endDate\":\"2099-12-31\",\"licenceName\":\"开户许可\",\"licenceNumber\":\"Z1000001091601\",\"showTypeName\":\"中国人民银行\",\"businessId\":\"4oz99c74e81c638ed6118212el0997e8\",\"detailShowType\":3,\"similarId\":0,\"fromDate\":\"2018-09-07\",\"licenceDepartment\":\"中国人民银行营业管理部\",\"oneSimilarInfo\":{\"licenceContent\":\"变更\",\"sourceId\":2,\"gid\":3367308,\"endDate\":\"\",\"licenceName\":\"\",\"licenceNumber\":\"Z1000001091601\",\"showTypeName\":\"信用中国\",\"similarId\":3815476,\"fromDate\":1536249600000,\"licenceDepartment\":\"中国人民银行营业管理部\",\"id\":115570553,\"originalId\":61183523,\"similarCount\":0},\"id\":3815476,\"originalId\":14977031,\"similarBusinessId\":\"e44m71v78bfbf448f8c77c1c2l537598\",\"similarCount\":1}          "
        },
        {
            "序号": "2",
            "决定日期/有效期自": "2017-09-29",
            "截止日期/有效期至": "2099-12-31",
            "许可文件编号/文书号": "Z1000001268702",
            "许可文件名称": "开户许可",
            "决定/许可机关": "中国人民银行营业管理部",
            "许可内容": "补换发  ",
            "数据来源": "中国人民银行",
            "操作": "            {\"licenceContent\":\"补换发\",\"sourceId\":3,\"oneSimilarShowType\":2,\"gid\":3367308,\"endDate\":\"2099-12-31\",\"licenceName\":\"开户许可\",\"licenceNumber\":\"Z1000001268702\",\"showTypeName\":\"中国人民银行\",\"businessId\":\"4evvzvema788af2babb8a919flaazec8\",\"detailShowType\":3,\"similarId\":0,\"fromDate\":\"2017-09-29\",\"licenceDepartment\":\"中国人民银行营业管理部\",\"oneSimilarInfo\":{\"licenceContent\":\"补换发\",\"sourceId\":2,\"gid\":3367308,\"endDate\":\"\",\"licenceName\":\"\",\"licenceNumber\":\"Z1000001268702\",\"showTypeName\":\"信用中国\",\"similarId\":7049792,\"fromDate\":1506614400000,\"licenceDepartment\":\"中国人民银行营业管理部\",\"id\":116672861,\"originalId\":61452966,\"similarCount\":0},\"id\":7049792,\"originalId\":16229268,\"similarBusinessId\":\"e4o1vzee6c8074419ea1f7178lf9vd88\",\"similarCount\":1}          "
        },
        {
            "序号": "3",
            "决定日期/有效期自": "2017-09-26",
            "截止日期/有效期至": "2099-12-31",
            "许可文件编号/文书号": "Z1000001268701",
            "许可文件名称": "开户许可",
            "决定/许可机关": "中国人民银行营业管理部",
            "许可内容": "变更  ",
            "数据来源": "中国人民银行",
            "操作": "            {\"licenceContent\":\"变更\",\"sourceId\":3,\"oneSimilarShowType\":2,\"gid\":3367308,\"endDate\":\"2099-12-31\",\"licenceName\":\"开户许可\",\"licenceNumber\":\"Z1000001268701\",\"showTypeName\":\"中国人民银行\",\"businessId\":\"4ev79vc90ddd5a0fe76722125l4291e8\",\"detailShowType\":3,\"similarId\":0,\"fromDate\":\"2017-09-26\",\"licenceDepartment\":\"中国人民银行营业管理部\",\"oneSimilarInfo\":{\"licenceContent\":\"变更\",\"sourceId\":2,\"gid\":3367308,\"endDate\":\"\",\"licenceName\":\"\",\"licenceNumber\":\"Z1000001268701\",\"showTypeName\":\"信用中国\",\"similarId\":8015188,\"fromDate\":1506355200000,\"licenceDepartment\":\"中国人民银行营业管理部\",\"id\":116819551,\"originalId\":61490340,\"similarCount\":0},\"id\":8015188,\"originalId\":16237207,\"similarBusinessId\":\"e4ozc7oc534304c7a9091919elb7c1a8\",\"similarCount\":1}          "
        },
        {
            "序号": "4",
            "决定日期/有效期自": "2017-09-15",
            "截止日期/有效期至": "2099-12-31",
            "许可文件编号/文书号": "J1000020203403",
            "许可文件名称": "开户许可",
            "决定/许可机关": "中国人民银行营业管理部",
            "许可内容": "变更  ",
            "数据来源": "中国人民银行",
            "操作": "            {\"licenceContent\":\"变更\",\"sourceId\":3,\"oneSimilarShowType\":2,\"gid\":3367308,\"endDate\":\"2099-12-31\",\"licenceName\":\"开户许可\",\"licenceNumber\":\"J1000020203403\",\"showTypeName\":\"中国人民银行\",\"businessId\":\"4e7eeom96fb69c42aa2e6b1b2l84e728\",\"detailShowType\":3,\"similarId\":0,\"fromDate\":\"2017-09-15\",\"licenceDepartment\":\"中国人民银行营业管理部\",\"oneSimilarInfo\":{\"licenceContent\":\"变更\",\"sourceId\":2,\"gid\":3367308,\"endDate\":\"\",\"licenceName\":\"\",\"licenceNumber\":\"J1000020203403\",\"showTypeName\":\"信用中国\",\"similarId\":7520589,\"fromDate\":1505404800000,\"licenceDepartment\":\"中国人民银行营业管理部\",\"id\":116754029,\"originalId\":61473608,\"similarCount\":0},\"id\":7520589,\"originalId\":16366487,\"similarBusinessId\":\"e4o97ecm802fcf101e8dd919el637118\",\"similarCount\":1}          "
        }
    ],
    "行政许可_数量": 4,
    "解析于": "2021-11-02T07:41:22.409Z",
    "解析账号": {
        "_id": "15697089347",
        "账号": 15697089347,
        "用户名": "赵子龙"
    },
    "购地信息": [
        {
            "序号": "1",
            "项目位置": "大兴区庞各庄镇",
            "土地用途": "公共设施用地",
            "面积": "2.8381公顷",
            "行政区": "大兴区",
            "供地方式": "划拨",
            "合同签订日期": "2013-01-28",
            "操作": ""
        },
        {
            "序号": "2",
            "项目位置": "大兴区青云店镇大谷店村村西",
            "土地用途": "公共设施用地",
            "面积": "4.9667公顷",
            "行政区": "北京市本级",
            "供地方式": "划拨",
            "合同签订日期": "2009-06-29",
            "操作": ""
        }
    ],
    "购地信息_数量": 2,
    "资质证书": [
        {
            "序号": "1",
            "发证日期": "2015-12-18",
            "证书类型": "施工许可信息",
            "产品名称及单元(主)": "-",
            "证书编号": "[2015]施建字0845号",
            "截止日期": "-",
            "操作": "详情"
        },
        {
            "序号": "2",
            "发证日期": "2013-09-25",
            "证书类型": "施工许可信息",
            "产品名称及单元(主)": "-",
            "证书编号": "[2013]施建字0626号",
            "截止日期": "-",
            "操作": "详情"
        },
        {
            "序号": "3",
            "发证日期": "2009-12-23",
            "证书类型": "施工许可信息",
            "产品名称及单元(主)": "-",
            "证书编号": "[2009]施装字1653号",
            "截止日期": "-",
            "操作": "详情"
        },
        {
            "序号": "4",
            "发证日期": "2009-10-23",
            "证书类型": "施工许可信息",
            "产品名称及单元(主)": "-",
            "证书编号": "[2009]施建字1290号",
            "截止日期": "-",
            "操作": "详情"
        },
        {
            "序号": "5",
            "发证日期": "2007-09-28",
            "证书类型": "施工许可信息",
            "产品名称及单元(主)": "-",
            "证书编号": "[2007]施建字1648号",
            "截止日期": "-",
            "操作": "详情"
        },
        {
            "序号": "6",
            "发证日期": "2006-09-27",
            "证书类型": "施工许可信息",
            "产品名称及单元(主)": "-",
            "证书编号": "[2006]施装字1905号",
            "截止日期": "-",
            "操作": "详情"
        },
        {
            "序号": "7",
            "发证日期": "2006-08-09",
            "证书类型": "施工许可信息",
            "产品名称及单元(主)": "-",
            "证书编号": "[2006]施建字1519号",
            "截止日期": "-",
            "操作": "详情"
        },
        {
            "序号": "8",
            "发证日期": "2006-06-29",
            "证书类型": "施工许可信息",
            "产品名称及单元(主)": "-",
            "证书编号": "[2006]施建字1203号",
            "截止日期": "-",
            "操作": "详情"
        },
        {
            "序号": "9",
            "发证日期": "2006-04-26",
            "证书类型": "施工许可信息",
            "产品名称及单元(主)": "-",
            "证书编号": "[2006]施建字0679号",
            "截止日期": "-",
            "操作": "详情"
        },
        {
            "序号": "10",
            "发证日期": "-",
            "证书类型": "安全监督编码信息",
            "产品名称及单元(主)": "-",
            "证书编号": "[2015]施建字0488号",
            "截止日期": "-",
            "操作": "详情"
        }
    ],
    "资质证书_数量": 10
}